odoo/addons/purchase_order_subscription/LICENSE
odoo/addons/purchase_order_subscription/README.rst
odoo/addons/purchase_order_subscription/__init__.py
odoo/addons/purchase_order_subscription/__manifest__.py
odoo/addons/purchase_order_subscription/data/purchase_order_data.xml
odoo/addons/purchase_order_subscription/i18n/de.po
odoo/addons/purchase_order_subscription/images/screen.png
odoo/addons/purchase_order_subscription/models/__init__.py
odoo/addons/purchase_order_subscription/models/purchase_order.py
odoo/addons/purchase_order_subscription/static/description/icon.png
odoo/addons/purchase_order_subscription/static/description/index.html
odoo/addons/purchase_order_subscription/views/purchase_order.xml
odoo_addon_purchase_order_subscription-18.0.1.0.0.dist-info/METADATA
odoo_addon_purchase_order_subscription-18.0.1.0.0.dist-info/WHEEL
odoo_addon_purchase_order_subscription-18.0.1.0.0.dist-info/top_level.txt
odoo_addon_purchase_order_subscription-18.0.1.0.0.dist-info/RECORD
